pybytom/__init__.py
pybytom/assets.py
pybytom/config.py
pybytom/exceptions.py
pybytom/rpc.py
pybytom/signature.py
pybytom/utils.py
pybytom/libs/__init__.py
pybytom/libs/ed25519.py
pybytom/libs/segwit.py
pybytom/script/__init__.py
pybytom/script/builder.py
pybytom/script/opcode.py
pybytom/script/script.py
pybytom/transaction/__init__.py
pybytom/transaction/actions.py
pybytom/transaction/tools.py
pybytom/transaction/transaction.py
pybytom/transaction/utils.py
pybytom/wallet/__init__.py
pybytom/wallet/tools.py
pybytom/wallet/utils.py
pybytom/wallet/wallet.py
pybytom-1.5.4.dist-info/LICENSE
pybytom-1.5.4.dist-info/METADATA
pybytom-1.5.4.dist-info/WHEEL
pybytom-1.5.4.dist-info/top_level.txt
pybytom-1.5.4.dist-info/RECORD
