Metadata-Version: 2.1
Name: pybytom
Version: 1.5.4
Summary: Python library with tools for Bytom mainchain and sidechain protocols.
Home-page: https://github.com/meherett/pybytom
Author: Meheret Tesfaye
Author-email: meherett@zoho.com
License: MIT
Keywords: bytom,vapor,mainchain,sidechain,wallet,protocol,blockchain
Platform: UNKNOWN
Classifier: Development Status :: 5 - Production/Stable
Classifier: License :: OSI Approved :: MIT License
Classifier: Programming Language :: Python :: 3.6
Classifier: Programming Language :: Python :: 3.7
Classifier: Programming Language :: Python :: 3.8
Classifier: Programming Language :: Python :: 3.9
Classifier: Topic :: Software Development :: Libraries :: Python Modules
Requires-Python: >=3.6,<4
Provides-Extra: tests
